jilei/__init__.py
jilei/dicom.py
jilei/docker_tools.py
jilei/mapping_3d_to_2d.py
jilei/medical_image_tools.py
jilei/mimics.py
jilei/mimics_qt.py
jilei/nnunet_tools.py
jilei/qt.py
jilei/system_tools.py
jilei/wxwork.py
jilei-0.2.3.dist-info/METADATA
jilei-0.2.3.dist-info/WHEEL
jilei-0.2.3.dist-info/top_level.txt
jilei-0.2.3.dist-info/RECORD
