Metadata-Version: 2.1
Name: jilei
Version: 0.2.3
Summary: For internal use.
Home-page: UNKNOWN
Author: jilei
Author-email: developer@jlzn.cc
License: UNKNOWN
Platform: UNKNOWN
Classifier: Programming Language :: Python :: 3
Classifier: License :: OSI Approved :: MIT License
Classifier: Operating System :: OS Independent
